CONTRIBUTING.md
MANIFEST.in
README.rst
_buildtest
setup.py
buildtest/__init__.py
buildtest/main.py
buildtest/__pycache__/__init__.cpython-36.pyc
buildtest/test/__init__.py
buildtest/test/binarytest.py
buildtest/test/compiler.py
buildtest/test/function.py
buildtest/test/job.py
buildtest/test/perl.py
buildtest/test/python.py
buildtest/test/r.py
buildtest/test/ruby.py
buildtest/test/sourcetest.py
buildtest/test/run/__init__.py
buildtest/test/run/app.py
buildtest/test/run/interactive.py
buildtest/test/run/system.py
buildtest/test/run/testname.py
buildtest/tools/__init__.py
buildtest/tools/build.py
buildtest/tools/cmake.py
buildtest/tools/config.py
buildtest/tools/easybuild.py
buildtest/tools/file.py
buildtest/tools/find.py
buildtest/tools/list.py
buildtest/tools/log.py
buildtest/tools/menu.py
buildtest/tools/modules.py
buildtest/tools/ohpc.py
buildtest/tools/options.py
buildtest/tools/print_functions.py
buildtest/tools/run.py
buildtest/tools/scan.py
buildtest/tools/software.py
buildtest/tools/system.py
buildtest/tools/utility.py
buildtest/tools/version.py
buildtest/tools/yaml.py
buildtest/tools/__pycache__/__init__.cpython-36.pyc
buildtest/tools/__pycache__/config.cpython-36.pyc
buildtest/tools/parser/__init__.py
buildtest/tools/parser/functions.py
buildtest/tools/parser/yaml_config.py
buildtest_framework.egg-info/PKG-INFO
buildtest_framework.egg-info/SOURCES.txt
buildtest_framework.egg-info/dependency_links.txt
buildtest_framework.egg-info/requires.txt
buildtest_framework.egg-info/top_level.txt
template/__init__.py
template/job.lsf
template/job.slurm
tests/__init__.py
tests/test_build.py
tests/test_config_file.py